hatch_timestamp_version/__init__.py
hatch_timestamp_version/_version.py
hatch_timestamp_version/hooks.py
hatch_timestamp_version/ts_scheme.py
hatch_timestamp_version-0.0.8.dist-info/METADATA
hatch_timestamp_version-0.0.8.dist-info/WHEEL
hatch_timestamp_version-0.0.8.dist-info/entry_points.txt
hatch_timestamp_version-0.0.8.dist-info/licenses/LICENSE
hatch_timestamp_version-0.0.8.dist-info/RECORD
