Metadata-Version: 2.4
Name: hatch-timestamp-version
Version: 0.0.8
Summary: plugin that provides a custom version scheme using UTC timestamps for development versions.
Project-URL: Homepage, https://github.com/viseshrp/hatch-timestamp-version
Project-URL: Repository, https://github.com/viseshrp/hatch-timestamp-version
Project-URL: Documentation, https://github.com/viseshrp/hatch-timestamp-version/blob/main/README.md
Project-URL: Changelog, https://github.com/viseshrp/hatch-timestamp-version/blob/main/CHANGELOG.md
Project-URL: Bug-Tracker, https://github.com/viseshrp/hatch-timestamp-version/issues
Project-URL: CI, https://github.com/viseshrp/hatch-timestamp-version/actions
Author-email: Visesh Prasad <viseshrprasad@gmail.com>
License: MIT
License-File: LICENSE
Keywords: python
Classifier: Development Status :: 4 - Beta
Classifier: Framework :: Hatch
Classifier: Intended Audience :: Developers
Classifier: License :: OSI Approved :: MIT License
Classifier: Natural Language :: English
Classifier: Operating System :: OS Independent
Classifier: Programming Language :: Python
Classifier: Programming Language :: Python :: 3
Classifier: Programming Language :: Python :: 3.9
Classifier: Programming Language :: Python :: 3.10
Classifier: Programming Language :: Python :: 3.11
Classifier: Programming Language :: Python :: 3.12
Classifier: Programming Language :: Python :: 3.13
Classifier: Topic :: Software Development :: Libraries :: Python Modules
Requires-Python: <4.0,>=3.9
Requires-Dist: hatch-vcs>=0.4.0
Requires-Dist: hatchling>=1.1.0
Requires-Dist: packaging>=25.0
